aws_lambda_publish_shared_event/__init__.py
aws_lambda_publish_shared_event/__main__.py
aws_lambda_publish_shared_event/util.py
aws_lambda_publish_shared_event/events/alb/alb.json
aws_lambda_publish_shared_event/events/alexa/alex-smart-home-skill-v1.json
aws_lambda_publish_shared_event/events/alexa/alex-smart-home-skill-v3.json
aws_lambda_publish_shared_event/events/alexa-skills-kit/end-session.json
aws_lambda_publish_shared_event/events/alexa-skills-kit/intent-answer.json
aws_lambda_publish_shared_event/events/alexa-skills-kit/intent-getnewfact.json
aws_lambda_publish_shared_event/events/alexa-skills-kit/intent-mycoloris.json
aws_lambda_publish_shared_event/events/alexa-skills-kit/intent-recipe.json
aws_lambda_publish_shared_event/events/alexa-skills-kit/start-session.json
aws_lambda_publish_shared_event/events/amazon-config/amazon-config.json
aws_lambda_publish_shared_event/events/amazon-connect/amazon-connect.json
aws_lambda_publish_shared_event/events/amazon-mq/active-mq.json
aws_lambda_publish_shared_event/events/amazon-mq/rabbit-mq.json
aws_lambda_publish_shared_event/events/amazon-msk/amazon-msk-1.json
aws_lambda_publish_shared_event/events/amazon-msk/amazon-msk-2.json
aws_lambda_publish_shared_event/events/apache-kafka/apache-kafka.json
aws_lambda_publish_shared_event/events/api-gateway/api-gateway-authorizer-format-1.json
aws_lambda_publish_shared_event/events/api-gateway/api-gateway-authorizer-format-2.json
aws_lambda_publish_shared_event/events/api-gateway/http-api-format-1.json
aws_lambda_publish_shared_event/events/api-gateway/http-api-format-2.json
aws_lambda_publish_shared_event/events/appsync/amplify-graphql-directive.json
aws_lambda_publish_shared_event/events/appsync/appsync-authorizer.json
aws_lambda_publish_shared_event/events/appsync/appsync-direct-resolver.json
aws_lambda_publish_shared_event/events/cloudformation/cloudformation-create.json
aws_lambda_publish_shared_event/events/cloudformation/cloudformation-delete.json
aws_lambda_publish_shared_event-0.20.0.dist-info/METADATA
aws_lambda_publish_shared_event-0.20.0.dist-info/WHEEL
aws_lambda_publish_shared_event-0.20.0.dist-info/entry_points.txt
aws_lambda_publish_shared_event-0.20.0.dist-info/top_level.txt
aws_lambda_publish_shared_event-0.20.0.dist-info/RECORD
