Metadata-Version: 2.1
Name: aws-lambda-publish-shared-event
Version: 0.20.0
Summary: Cli to publish shareable Lambda test events.
Home-page: https://lambda.101i.de/
Author: Michael Brewer
License: MIT
Project-URL: GitHub, https://github.com/michaelbrewer/aws-lambda-events
Project-URL: Documentation, https://lambda.101i.de/
Classifier: Development Status :: 4 - Beta
Classifier: Environment :: Console
Classifier: Intended Audience :: Developers
Classifier: License :: OSI Approved :: MIT License
Classifier: Natural Language :: English
Classifier: Operating System :: OS Independent
Classifier: Programming Language :: Python :: 3.7
Classifier: Programming Language :: Python :: 3.8
Classifier: Programming Language :: Python :: 3.9
Classifier: Programming Language :: Python :: 3.10
Requires-Python: >=3.7
Requires-Dist: boto3 (>=1.26.15)
Requires-Dist: botocore (>=1.29.15)
Requires-Dist: pick (>=2.2.0)
